mirror/__init__.py
mirror/bus.py
mirror/color.py
mirror/common.py
mirror/component.py
mirror/config.py
mirror/configmanager.py
mirror/console.py
mirror/daemon.py
mirror/error.py
mirror/event.py
mirror/eventmanager.py
mirror/handler.py
mirror/log.py
mirror/main.py
mirror/pluginbase.py
mirror/plugininit.py
mirror/pluginmanager.py
mirror/pluginthread.py
mirror/queue.py
mirror/scheduler.py
mirror/sysinfo.py
mirror/task.py
mirror/i18n/zh_CN/LC_MESSAGES/mirror.mo
mirror/plugins/Notifier-0.1.9-py2.7.egg
mirror/plugins/Notifier-0.1.9-py3.8.egg
mirror/plugins/SlateFish-0.6-py2.7.egg
mirror/plugins/SlateFish-0.6-py3.8.egg
mirror/plugins/SystemTask-0.6-py2.7.egg
mirror/plugins/SystemTask-0.6-py3.8.egg
mirror/plugins/TaskStatus-0.6-py2.7.egg
mirror/plugins/TaskStatus-0.6-py3.8.egg
mirror-0.8.2.data/data/lib/systemd/system/mirrord@.service
mirror-0.8.2.data/data/share/bash-completion/completions/mirrord
mirror-0.8.2.data/data/share/man/man1/mirrord.1
mirror-0.8.2.data/data/share/mirror/etc/mirror.ini
mirror-0.8.2.data/data/share/zsh/site-functions/_mirrord
mirror-0.8.2.dist-info/AUTHORS
mirror-0.8.2.dist-info/LICENSE
mirror-0.8.2.dist-info/METADATA
mirror-0.8.2.dist-info/WHEEL
mirror-0.8.2.dist-info/entry_points.txt
mirror-0.8.2.dist-info/top_level.txt
mirror-0.8.2.dist-info/RECORD
