Metadata-Version: 2.1
Name: mirror
Version: 0.8.2
Summary: Mirror for open source mirror site to sync files
Home-page: http://mirror.bjtu.edu.cn
Author: Shang Yuanchun, Bob Gao
Author-email: Shang Yuanchun <idealities@gmail.com>, Bob Gao <gaobo@bjtu.edu.cn>
License: GPLv3
Keywords: open source mirror
Platform: UNKNOWN
Classifier: License :: OSI Approved :: GNU General Public License v3 (GPLv3)
Classifier: Operating System :: OS Independent
Classifier: Programming Language :: Python
Classifier: Programming Language :: Python :: 2
Classifier: Programming Language :: Python :: 2.7
Classifier: Programming Language :: Python :: 3
Classifier: Programming Language :: Python :: 3.5
Classifier: Programming Language :: Python :: 3.6
Classifier: Programming Language :: Python :: 3.7
Classifier: Programming Language :: Python :: 3.8
Requires-Python: >=2.7,!=3.0.*,!=3.1.*,!=3.2.*,!=3.3.*,!=3.4.*
